plover_combo/combo_colors.py
plover_combo/combo_config.py
plover_combo/combo_ui.py
plover_combo/config_ui.py
plover_combo/resources_rc.py
plover_combo-2.0.0.dist-info/licenses/LICENSE.txt
plover_combo-2.0.0.dist-info/METADATA
plover_combo-2.0.0.dist-info/WHEEL
plover_combo-2.0.0.dist-info/entry_points.txt
plover_combo-2.0.0.dist-info/top_level.txt
plover_combo-2.0.0.dist-info/zip-safe
plover_combo-2.0.0.dist-info/RECORD
