Metadata-Version: 2.4
Name: plover-combo
Version: 2.0.0
Summary: Combo Mode for Plover
Home-page: https://github.com/Kaoffie/plover_combo
Author: Kaoffie
Author-email: kaoffie@gmail.com
License: MIT License (MIT)
Keywords: plover plover_plugin
Classifier: Development Status :: 5 - Production/Stable
Classifier: Environment :: Plugins
Classifier: Intended Audience :: End Users/Desktop
Classifier: License :: OSI Approved :: MIT License
Classifier: Operating System :: OS Independent
Classifier: Programming Language :: Python :: 3
Classifier: Programming Language :: Python :: 3.6
License-File: LICENSE.txt
Requires-Dist: plover>=5.0.0.dev2
Dynamic: license-file
